django_composer-0.0.5.dist-info/pbr.json
django_composer-0.0.5.dist-info/METADATA
django_composer-0.0.5.dist-info/metadata.json
django_composer-0.0.5.dist-info/DESCRIPTION.rst
django_composer-0.0.5.dist-info/top_level.txt
django_composer-0.0.5.dist-info/RECORD
django_composer-0.0.5.dist-info/WHEEL
composer/models.py
composer/admin.py
composer/views.py
composer/__init__.py
composer/urls.py
composer/static/css/composer.css
composer/static/js/composer.js
composer/static/js/composer.min.js
composer/templatetags/composer.py
composer/templatetags/__init__.py
composer/templatetags/__pycache__/composer.cpython-34.pyc
composer/templatetags/__pycache__/__init__.cpython-34.pyc
composer/templates/composer/example.html
composer/templates/composer/edit.html
composer/migrations/0001_initial.py
composer/migrations/__init__.py
composer/migrations/__pycache__/__init__.cpython-34.pyc
composer/migrations/__pycache__/0001_initial.cpython-34.pyc
composer/__pycache__/models.cpython-34.pyc
composer/__pycache__/views.cpython-34.pyc
composer/__pycache__/__init__.cpython-34.pyc
composer/__pycache__/urls.cpython-34.pyc
