Metadata-Version: 2.0
Name: django-composer
Version: 0.0.5
Summary: Simple Django app for adding dynamic text and markup to templates and views.
Home-page: https://github.com/featherweightweb/django-composer
Author: Benjamin Dummer
Author-email: ben@featherweightweb.com
License: MIT License
Download-URL: https://github.com/featherweightweb/django-composer/tarball/0.0.5
Platform: UNKNOWN
Classifier: Development Status :: 3 - Alpha
Classifier: Environment :: Web Environment
Classifier: Framework :: Django
Classifier: Intended Audience :: Developers
Classifier: Operating System :: OS Independent
Classifier: License :: OSI Approved :: MIT License
Classifier: Programming Language :: Python :: 3
Classifier: Programming Language :: Python :: 3.3
Classifier: Programming Language :: Python :: 3.4
